super_scad_circle_plus/CircleSector.py
super_scad_circle_plus/CircleSegment.py
super_scad_circle_plus/Ellipse.py
super_scad_circle_plus/Ellipsoid.py
super_scad_circle_plus/__init__.py
super_scad_circle_plus-0.9.10.dist-info/LICENSE
super_scad_circle_plus-0.9.10.dist-info/METADATA
super_scad_circle_plus-0.9.10.dist-info/WHEEL
super_scad_circle_plus-0.9.10.dist-info/RECORD
